boogle_logger/__init__.py
boogle_logger-99.99.99.dist-info/METADATA
boogle_logger-99.99.99.dist-info/WHEEL
boogle_logger-99.99.99.dist-info/top_level.txt
boogle_logger-99.99.99.dist-info/RECORD
