Metadata-Version: 2.4
Name: boogle-logger
Version: 99.99.99
Summary: Dependency Confusion Attack Demo
Author: Attacker
Requires-Python: >=3.6
Dynamic: author
Dynamic: requires-python
Dynamic: summary
